[
  {
    "id": 3217554273635329000,
    "resource_state": 2,
    "name": "Were you going up, or down the slope?",
    "activity": {
      "id": 11240476254,
      "visibility": "followers_only",
      "resource_state": 1
    },
    "athlete": {
      "id": 42137242,
      "resource_state": 1
    },
    "elapsed_time": 92,
    "moving_time": 92,
    "start_date": "2024-04-22T13:02:33Z",
    "start_date_local": "2024-04-22T14:02:33Z",
    "distance": 570,
    "start_index": 29,
    "end_index": 121,
    "device_watts": false,
    "segment": {
      "id": 28442092,
      "resource_state": 2,
      "name": "Were you going up, or down the slope?",
      "activity_type": "Ride",
      "distance": 570,
      "average_grade": -0.1,
      "maximum_grade": 1.9,
      "elevation_high": 34.9,
      "elevation_low": 33.4,
      "start_latlng": [
        55.961675,
        -3.170731
      ],
      "end_latlng": [
        55.963342,
        -3.162777
      ],
      "elevation_profile": null,
      "elevation_profiles": null,
      "climb_category": 0,
      "city": "Edinburgh",
      "state": "Scotland",
      "country": "United Kingdom",
      "private": false,
      "hazardous": false,
      "starred": false
    },
    "pr_rank": null,
    "achievements": [],
    "visibility": "only_me",
    "hidden": false
  },
  {
    "id": 3217554273636688000,
    "resource_state": 2,
    "name": "Down to the D&C",
    "activity": {
      "id": 11240476254,
      "visibility": "followers_only",
      "resource_state": 1
    },
    "athlete": {
      "id": 42137242,
      "resource_state": 1
    },
    "elapsed_time": 266,
    "moving_time": 215,
    "start_date": "2024-04-22T13:04:43Z",
    "start_date_local": "2024-04-22T14:04:43Z",
    "distance": 1323.7,
    "start_index": 159,
    "end_index": 376,
    "device_watts": false,
    "segment": {
      "id": 11706034,
      "resource_state": 2,
      "name": "Down to the D&C",
      "activity_type": "Ride",
      "distance": 1323.7,
      "average_grade": -1.4,
      "maximum_grade": 3.7,
      "elevation_high": 29.6,
      "elevation_low": 11.1,
      "start_latlng": [
        55.963877,
        -3.162381
      ],
      "end_latlng": [
        55.969431,
        -3.14503
      ],
      "elevation_profile": null,
      "elevation_profiles": null,
      "climb_category": 0,
      "city": null,
      "state": null,
      "country": null,
      "private": false,
      "hazardous": true,
      "starred": false
    },
    "pr_rank": null,
    "achievements": [],
    "visibility": "followers_only",
    "hidden": true
  },
  {
    "id": 3217554273634678000,
    "resource_state": 2,
    "name": "Stinky Bum to Cat and Dog Home",
    "activity": {
      "id": 11240476254,
      "visibility": "followers_only",
      "resource_state": 1
    },
    "athlete": {
      "id": 42137242,
      "resource_state": 1
    },
    "elapsed_time": 150,
    "moving_time": 150,
    "start_date": "2024-04-22T13:09:15Z",
    "start_date_local": "2024-04-22T14:09:15Z",
    "distance": 787.9,
    "start_index": 382,
    "end_index": 532,
    "device_watts": false,
    "segment": {
      "id": 31005853,
      "resource_state": 2,
      "name": "Stinky Bum to Cat and Dog Home",
      "activity_type": "Ride",
      "distance": 787.9,
      "average_grade": 0.6,
      "maximum_grade": 3.6,
      "elevation_high": 16,
      "elevation_low": 10.2,
      "start_latlng": [
        55.969485,
        -3.144592
      ],
      "end_latlng": [
        55.966789,
        -3.13342
      ],
      "elevation_profile": null,
      "elevation_profiles": null,
      "climb_category": 0,
      "city": "Edinburgh",
      "state": "Scotland",
      "country": "United Kingdom",
      "private": false,
      "hazardous": false,
      "starred": false
    },
    "pr_rank": null,
    "achievements": [],
    "visibility": "followers_only",
    "hidden": true
  },
  {
    "id": 3217554273634117600,
    "resource_state": 2,
    "name": "Seafield Sprint then Clinb",
    "activity": {
      "id": 11240476254,
      "visibility": "followers_only",
      "resource_state": 1
    },
    "athlete": {
      "id": 42137242,
      "resource_state": 1
    },
    "elapsed_time": 86,
    "moving_time": 86,
    "start_date": "2024-04-22T13:09:22Z",
    "start_date_local": "2024-04-22T14:09:22Z",
    "distance": 457,
    "start_index": 389,
    "end_index": 475,
    "device_watts": false,
    "segment": {
      "id": 18397522,
      "resource_state": 2,
      "name": "Seafield Sprint then Clinb",
      "activity_type": "Ride",
      "distance": 457,
      "average_grade": 0.9,
      "maximum_grade": 2.9,
      "elevation_high": 95,
      "elevation_low": 89.6,
      "start_latlng": [
        55.969376,
        -3.144065
      ],
      "end_latlng": [
        55.967943,
        -3.137215
      ],
      "elevation_profile": null,
      "elevation_profiles": null,
      "climb_category": 0,
      "city": "Edinburgh",
      "state": "Scotland",
      "country": "United Kingdom",
      "private": false,
      "hazardous": false,
      "starred": false
    },
    "pr_rank": null,
    "achievements": [],
    "visibility": "followers_only",
    "hidden": false
  },
  {
    "id": 3217554273635156000,
    "resource_state": 2,
    "name": "Get off the pavement!",
    "activity": {
      "id": 11240476254,
      "visibility": "followers_only",
      "resource_state": 1
    },
    "athlete": {
      "id": 42137242,
      "resource_state": 1
    },
    "elapsed_time": 132,
    "moving_time": 132,
    "start_date": "2024-04-22T13:09:44Z",
    "start_date_local": "2024-04-22T14:09:44Z",
    "distance": 704.9,
    "start_index": 411,
    "end_index": 543,
    "device_watts": false,
    "segment": {
      "id": 7196024,
      "resource_state": 2,
      "name": "Get off the pavement!",
      "activity_type": "Ride",
      "distance": 704.9,
      "average_grade": 0.2,
      "maximum_grade": 2,
      "elevation_high": 10.6,
      "elevation_low": 7.6,
      "start_latlng": [
        55.968998,
        -3.142441
      ],
      "end_latlng": [
        55.96632,
        -3.132816
      ],
      "elevation_profile": null,
      "elevation_profiles": null,
      "climb_category": 0,
      "city": "Edinburgh",
      "state": "Scotland",
      "country": "United Kingdom",
      "private": false,
      "hazardous": false,
      "starred": false
    },
    "pr_rank": null,
    "achievements": [],
    "visibility": "followers_only",
    "hidden": false
  },
  {
    "id": 3217554273635095600,
    "resource_state": 2,
    "name": "short sprint",
    "activity": {
      "id": 11240476254,
      "visibility": "followers_only",
      "resource_state": 1
    },
    "athlete": {
      "id": 42137242,
      "resource_state": 1
    },
    "elapsed_time": 133,
    "moving_time": 133,
    "start_date": "2024-04-22T13:12:05Z",
    "start_date_local": "2024-04-22T14:12:05Z",
    "distance": 792.6,
    "start_index": 552,
    "end_index": 685,
    "device_watts": false,
    "segment": {
      "id": 10525064,
      "resource_state": 2,
      "name": "short sprint",
      "activity_type": "Ride",
      "distance": 792.6,
      "average_grade": -0.2,
      "maximum_grade": 0.5,
      "elevation_high": 9.9,
      "elevation_low": 5.2,
      "start_latlng": [
        55.966026,
        -3.132229
      ],
      "end_latlng": [
        55.960936,
        -3.123495
      ],
      "elevation_profile": null,
      "elevation_profiles": null,
      "climb_category": 0,
      "city": "Edinburgh",
      "state": null,
      "country": "United Kingdom",
      "private": false,
      "hazardous": false,
      "starred": false
    },
    "pr_rank": null,
    "achievements": [],
    "visibility": "followers_only",
    "hidden": false
  },
  {
    "id": 3217554273636627500,
    "resource_state": 2,
    "name": "dodging scooters and dogs :)",
    "activity": {
      "id": 11240476254,
      "visibility": "followers_only",
      "resource_state": 1
    },
    "athlete": {
      "id": 42137242,
      "resource_state": 1
    },
    "elapsed_time": 189,
    "moving_time": 189,
    "start_date": "2024-04-22T13:12:05Z",
    "start_date_local": "2024-04-22T14:12:05Z",
    "distance": 1106.9,
    "start_index": 552,
    "end_index": 741,
    "device_watts": false,
    "segment": {
      "id": 10524990,
      "resource_state": 2,
      "name": "dodging scooters and dogs :)",
      "activity_type": "Ride",
      "distance": 1106.9,
      "average_grade": -0.5,
      "maximum_grade": 0.9,
      "elevation_high": 9.9,
      "elevation_low": 3,
      "start_latlng": [
        55.966026,
        -3.132229
      ],
      "end_latlng": [
        55.958872,
        -3.120065
      ],
      "elevation_profile": null,
      "elevation_profiles": null,
      "climb_category": 0,
      "city": "Edinburgh",
      "state": null,
      "country": "United Kingdom",
      "private": false,
      "hazardous": false,
      "starred": false
    },
    "pr_rank": null,
    "achievements": [],
    "visibility": "followers_only",
    "hidden": true
  },
  {
    "id": 3217554273633101000,
    "resource_state": 2,
    "name": "Behind The Garages Sprint Eastbound",
    "activity": {
      "id": 11240476254,
      "visibility": "followers_only",
      "resource_state": 1
    },
    "athlete": {
      "id": 42137242,
      "resource_state": 1
    },
    "elapsed_time": 184,
    "moving_time": 184,
    "start_date": "2024-04-22T13:12:16Z",
    "start_date_local": "2024-04-22T14:12:16Z",
    "distance": 1072.82,
    "start_index": 563,
    "end_index": 747,
    "device_watts": false,
    "segment": {
      "id": 1473561,
      "resource_state": 2,
      "name": "Behind The Garages Sprint Eastbound",
      "activity_type": "Ride",
      "distance": 1072.82,
      "average_grade": 0,
      "maximum_grade": 3.9,
      "elevation_high": 9.5,
      "elevation_low": 3.1,
      "start_latlng": [
        55.96571612768041,
        -3.1312523740900944
      ],
      "end_latlng": [
        55.958646107760785,
        -3.1197469097724295
      ],
      "elevation_profile": null,
      "elevation_profiles": null,
      "climb_category": 0,
      "city": "Edinburgh",
      "state": "City of Edinburgh",
      "country": "United Kingdom",
      "private": false,
      "hazardous": false,
      "starred": false
    },
    "pr_rank": null,
    "achievements": [],
    "visibility": "followers_only",
    "hidden": false
  },
  {
    "id": 3217554273632622600,
    "resource_state": 2,
    "name": "Seafield 300m",
    "activity": {
      "id": 11240476254,
      "visibility": "followers_only",
      "resource_state": 1
    },
    "athlete": {
      "id": 42137242,
      "resource_state": 1
    },
    "elapsed_time": 59,
    "moving_time": 59,
    "start_date": "2024-04-22T13:45:53Z",
    "start_date_local": "2024-04-22T14:45:53Z",
    "distance": 290.6,
    "start_index": 1199,
    "end_index": 1258,
    "device_watts": false,
    "segment": {
      "id": 4905760,
      "resource_state": 2,
      "name": "Seafield 300m",
      "activity_type": "Ride",
      "distance": 290.6,
      "average_grade": 0.1,
      "maximum_grade": 27.6,
      "elevation_high": 12,
      "elevation_low": 3,
      "start_latlng": [
        55.958583,
        -3.119581
      ],
      "end_latlng": [
        55.96045,
        -3.122815
      ],
      "elevation_profile": null,
      "elevation_profiles": null,
      "climb_category": 0,
      "city": "Edinburgh",
      "state": "Scotland",
      "country": "United Kingdom",
      "private": false,
      "hazardous": true,
      "starred": false
    },
    "pr_rank": null,
    "achievements": [],
    "visibility": "followers_only",
    "hidden": true
  },
  {
    "id": 3217554273633250300,
    "resource_state": 2,
    "name": "After the prom.",
    "activity": {
      "id": 11240476254,
      "visibility": "followers_only",
      "resource_state": 1
    },
    "athlete": {
      "id": 42137242,
      "resource_state": 1
    },
    "elapsed_time": 235,
    "moving_time": 235,
    "start_date": "2024-04-22T13:45:56Z",
    "start_date_local": "2024-04-22T14:45:56Z",
    "distance": 1130.67,
    "start_index": 1202,
    "end_index": 1437,
    "device_watts": false,
    "segment": {
      "id": 765767,
      "resource_state": 2,
      "name": "After the prom.",
      "activity_type": "Ride",
      "distance": 1130.67,
      "average_grade": 0.2,
      "maximum_grade": 2.2,
      "elevation_high": 63,
      "elevation_low": 60,
      "start_latlng": [
        55.95867870641303,
        -3.1197690787711836
      ],
      "end_latlng": [
        55.966029341233934,
        -3.1321697440710965
      ],
      "elevation_profile": null,
      "elevation_profiles": null,
      "climb_category": 0,
      "city": "Edinburgh",
      "state": "City of Edinburgh",
      "country": "United Kingdom",
      "private": false,
      "hazardous": true,
      "starred": false
    },
    "pr_rank": null,
    "achievements": [],
    "visibility": "followers_only",
    "hidden": true
  },
  {
    "id": 3217554273634031600,
    "resource_state": 2,
    "name": "Cat and dog climb",
    "activity": {
      "id": 11240476254,
      "visibility": "followers_only",
      "resource_state": 1
    },
    "athlete": {
      "id": 42137242,
      "resource_state": 1
    },
    "elapsed_time": 48,
    "moving_time": 48,
    "start_date": "2024-04-22T13:49:03Z",
    "start_date_local": "2024-04-22T14:49:03Z",
    "distance": 194,
    "start_index": 1389,
    "end_index": 1437,
    "device_watts": false,
    "segment": {
      "id": 13043125,
      "resource_state": 2,
      "name": "Cat and dog climb",
      "activity_type": "Ride",
      "distance": 194,
      "average_grade": 1.7,
      "maximum_grade": 3.8,
      "elevation_high": 10.2,
      "elevation_low": 6.7,
      "start_latlng": [
        55.964996,
        -3.129969
      ],
      "end_latlng": [
        55.966,
        -3.132231
      ],
      "elevation_profile": null,
      "elevation_profiles": null,
      "climb_category": 0,
      "city": "Edinburgh",
      "state": "Scotland",
      "country": "United Kingdom",
      "private": false,
      "hazardous": true,
      "starred": false
    },
    "pr_rank": null,
    "achievements": [],
    "visibility": "followers_only",
    "hidden": true
  },
  {
    "id": 3217554273631718400,
    "resource_state": 2,
    "name": "Eat, Sleep, Rave, Repeat...",
    "activity": {
      "id": 11240476254,
      "visibility": "followers_only",
      "resource_state": 1
    },
    "athlete": {
      "id": 42137242,
      "resource_state": 1
    },
    "elapsed_time": 39,
    "moving_time": 39,
    "start_date": "2024-04-22T13:53:43Z",
    "start_date_local": "2024-04-22T14:53:43Z",
    "distance": 158.6,
    "start_index": 1609,
    "end_index": 1648,
    "device_watts": false,
    "segment": {
      "id": 5918052,
      "resource_state": 2,
      "name": "Eat, Sleep, Rave, Repeat...",
      "activity_type": "Ride",
      "distance": 158.6,
      "average_grade": 4.2,
      "maximum_grade": 17.3,
      "elevation_high": 7,
      "elevation_low": 0.4,
      "start_latlng": [
        55.969516,
        -3.144675
      ],
      "end_latlng": [
        55.968402,
        -3.146263
      ],
      "elevation_profile": null,
      "elevation_profiles": null,
      "climb_category": 0,
      "city": "Edinburgh",
      "state": "Scotland",
      "country": "United Kingdom",
      "private": false,
      "hazardous": false,
      "starred": false
    },
    "pr_rank": null,
    "achievements": [],
    "visibility": "followers_only",
    "hidden": false
  },
  {
    "id": 3217554273630050300,
    "resource_state": 2,
    "name": "Restalrig Railway Path Uphill",
    "activity": {
      "id": 11240476254,
      "visibility": "followers_only",
      "resource_state": 1
    },
    "athlete": {
      "id": 42137242,
      "resource_state": 1
    },
    "elapsed_time": 209,
    "moving_time": 209,
    "start_date": "2024-04-22T13:54:42Z",
    "start_date_local": "2024-04-22T14:54:42Z",
    "distance": 1131.86,
    "start_index": 1668,
    "end_index": 1877,
    "device_watts": false,
    "segment": {
      "id": 1594509,
      "resource_state": 2,
      "name": "Restalrig Railway Path Uphill",
      "activity_type": "Ride",
      "distance": 1131.86,
      "average_grade": 0.8,
      "maximum_grade": 22.8,
      "elevation_high": 34.2,
      "elevation_low": 18.1,
      "start_latlng": [
        55.96822966499327,
        -3.146932056830286
      ],
      "end_latlng": [
        55.963853521332815,
        -3.1623221132662263
      ],
      "elevation_profile": null,
      "elevation_profiles": null,
      "climb_category": 0,
      "city": "Edinburgh",
      "state": "City of Edinburgh",
      "country": "United Kingdom",
      "private": false,
      "hazardous": true,
      "starred": false
    },
    "pr_rank": null,
    "achievements": [],
    "visibility": "followers_only",
    "hidden": true
  },
  {
    "id": 3217554273630358500,
    "resource_state": 2,
    "name": "3 Fingers of Death",
    "activity": {
      "id": 11240476254,
      "visibility": "followers_only",
      "resource_state": 1
    },
    "athlete": {
      "id": 42137242,
      "resource_state": 1
    },
    "elapsed_time": 28,
    "moving_time": 22,
    "start_date": "2024-04-22T13:58:15Z",
    "start_date_local": "2024-04-22T14:58:15Z",
    "distance": 108.6,
    "start_index": 1881,
    "end_index": 1908,
    "device_watts": false,
    "segment": {
      "id": 13838462,
      "resource_state": 2,
      "name": "3 Fingers of Death",
      "activity_type": "Ride",
      "distance": 108.6,
      "average_grade": 1.6,
      "maximum_grade": 20.1,
      "elevation_high": 31.7,
      "elevation_low": 30,
      "start_latlng": [
        55.963768,
        -3.162571
      ],
      "end_latlng": [
        55.963349,
        -3.162489
      ],
      "elevation_profile": null,
      "elevation_profiles": null,
      "climb_category": 0,
      "city": "Edinburgh",
      "state": "Scotland",
      "country": "United Kingdom",
      "private": false,
      "hazardous": true,
      "starred": false
    },
    "pr_rank": null,
    "achievements": [],
    "visibility": "followers_only",
    "hidden": true
  }
]